tsfontconverter/__init__.py
tsfontconverter/tsfontconverter.py
tsfontconverter/fontmodel/CharacterMap.py
tsfontconverter/fontmodel/Font.py
tsfontconverter/fontmodel/FontStandard.py
tsfontconverter/fontmodel/Glyph.py
tsfontconverter/fontmodel/Meta.py
tsfontconverter/fontmodel/__init__.py
tsfontconverter/fontparser/__init__.py
tsfontconverter/fontparser/fontparser.py
tsfontconverter/fontparser/reflectionutils.py
tsfontconverter/typescript/pytsconverter.py
tsfontconverter-0.35.dist-info/entry_points.txt
tsfontconverter-0.35.dist-info/LICENSE
tsfontconverter-0.35.dist-info/WHEEL
tsfontconverter-0.35.dist-info/METADATA
tsfontconverter-0.35.dist-info/RECORD
