Metadata-Version: 2.1
Name: tsfontconverter
Version: 0.35
Summary: Converts fonts to TypeScript objects
Author-email: Thor Christopher Arisland <thor.arisland@gmail.com>
Requires-Python: >=3.8
Classifier: Programming Language :: Python :: 3
Classifier: License :: OSI Approved :: Apache Software License
Classifier: Operating System :: OS Independent
Requires-Dist: fonttools
Requires-Dist: pytest
Requires-Dist: python-dotenv
